Workbook

Sheet 填写注意事项
A2: 1、项目中心模糊查找功能使用仅适用单字查找，输入关键单字按回车键-点击下拉键-按上下键+回车键选择相应项目中心
A16: 2、研发费用与差旅费分开提交2张单据，研发费用在单据表；若无相应项目中心，则填写“其他”；则在出行人及备注填写实际项目名称/临时用项目名称；凡填其他项目，备注栏必填实际项目名称
A17: 3、行程信息以单个项目为准填写，根据实际单个项目填写时间和地点，时间间隔涉及到多个项目，可以同一时间段重复。连续时间涉及多个项目，或按项目个数均分或者实际发生额按单个项目填写多条信息。
A18: 4、多个临时项目均分同一费用，需按单个项目填写，例如：滴滴发票共1200，有10个项目平均分，则需要填写10条费用明细；
A19: 5、请报销人注意，避免重复提交电子发票，金蝶系统有自动查重功能，发票金额会自动去除重复发票金额，导致报销金额大于发票金额，产生差异；需要手工查找重复发票，会延迟报销收款时间；
A20: 6、出租车卷式发票和ETC针式打印票如果打印不清楚，用铅笔在打印金额旁重新写一遍，避免核对金额不符。
A21: 7、取消“员工报销单模板”密码保护，请勿改动相关公式
A22: 8、增加 发票对应 填写摘要
A23: 9、增加费用种类

Sheet 员工报销单模板
AA1: 填写注意：灰色格子已经设置公式，勿改动 | AB1: 黄色必填 | AC1: 报销人姓名 | AG1: 报销总金额 | AH1: =SUM(AJ6:AJ200) -> 1500 | AR1: 已设置单个字-模糊查找，只需要输入部分项目字段，点击下拉键，选择对应项目中心
C2: 报销申请日期 | D2: 此处固定格式，按范例填写即可，不需要更改 | E2: 此处固定格式，按范例填写即可，不需要更改 | F2: 已设好公式，自动生成，不需要手工填 | G2: 选择组织，下拉选项 | H2: 按实际填写事由 | I2: 报销人编码 | J2: 报销人的名字（此处为范例，导入金蝶后需要手动变更为对应报销人） | K2: 已设好公式，自动生成，不需要手工填 | L2: 报销人所属部门名称（注意从“客服4组”往下是凌跃的部门） | M2: 此处固定格式，按范例填写即可，不需要更改 | N2: 此处固定格式，按范例填写即可，不需要更改 | O2: 已设好公式，自动生成，不需要手工填 | P2: 已设好公式，自动生成，不需要手工填 | Q2: 已设好公式，自动生成，不需要手工填 | R2: 已设好公式，自动生成，不需要手工填 | S2: 收款对象类型默认为员工，按范例填写即可，不需要更改 | T2: 收款人编码 | U2: 收款人的名字（此处为范例，导入金蝶后需要手动变更为对应收款人） | V2: 此处固定格式，按范例填写即可，不需要更改 | AA2: 文本格式，六位数，自己编 | AB2: 已设好公式，自动生成，不需要手工填 | AC2: 下拉选择 | AD2: 日期格式：XXXX-XX-XX 根据实际单个项目填写时间和地点。连续时间涉及多个项目，或按项目个数均分或者实际发生按单个项目填写多条信息。 | AE2: 日期格式：XXXX-XX-XX 根据实际单个项目填写时间和地点。连续时间涉及多个项目，或按项目个数均分或者实际发生按单个项目填写多条信息。 | AF2: 根据实际单个项目填写时间和地点。连续时间涉及多个项目，或按项目个数均分或者实际发生按单个项目填写多条信息。 | AG2: 根据实际单个项目填写时间和地点。连续时间涉及多个项目，或按项目个数均分或者实际发生按单个项目填写多条信息。 | AH2: 已设好公式，自动生成，不需要手工填 | AI2: 下拉选择 | AJ2: 按实际填 | AK2: 下拉选择， 增值税发票=增值税专用发票 | AL2: 已设好公式，自动生成，不需要手工填 | AM2: 已设好公式，自动生成，不需要手工填 | AN2: 已设好公式，自动生成，不需要手工填 | AO2: 下拉选项（注意从客服4组往下是凌跃的部门） | AP2: 已设好公式，自动生成，不需要手工填 | AQ2: 已设好公式，自动生成，不需要手工填 | AR2: 如果没有对应的项目中心和项目编号，填其他和000573，并在备注烂填写临时项目名称 | AS2: 按实际填写，住宿天数和实际项目中心（项目中心栏填“其他”必填）
B3: FBillHead(ER_ExpReimbursement_Travel) | C3: FDate | D3: FCurrencyID | E3: FCurrencyID#Name | F3: FOrgID | G3: FOrgID#Name | H3: FCausa | I3: FProposerID | J3: FProposerID#Name | K3: FRequestDeptID | L3: FRequestDeptID#Name | M3: FBillTypeID | N3: FBillTypeID#Name | O3: FExpenseOrgId | P3: FExpenseOrgId#Name | Q3: FExpenseDeptID | R3: FExpenseDeptID#Name | S3: FCONTACTUNITTYPE | T3: FCONTACTUNIT | U3: FCONTACTUNIT#Name | V3: FExchangeTypeID | W3: FExchangeTypeID#Name | X3: FLocCurrencyID | Y3: FLocCurrencyID#Name | AA3: FEntity | AB3: FExpID | AC3: FExpID#Name | AD3: FTravelStartDate | AE3: FTravelEndDate | AF3: FTravelStartSite | AG3: FTravelEndSite | AH3: FTravelType | AI3: FTravelType#Name | AJ3: FTravelAmount | AK3: FInvoiceType | AL3: FTaxRate | AM3: FExpenseAmount | AN3: FExpenseDeptEntryID | AO3: FExpenseDeptEntryID#Name | AP3: FTaxSubmitAmt | AQ3: F_DH_Project | AR3: F_DH_Project#Name | AS3: FRemark
B4: *单据头(序号) | C4: *(单据头)申请日期 | D4: *(单据头)币别#编码 | E4: (单据头)币别#名称 | F4: *(单据头)申请组织#编码 | G4: (单据头)申请组织#名称 | H4: *(单据头)事由 | I4: *(单据头)申请人#编码 | J4: (单据头)申请人#名称 | K4: *(单据头)申请部门#编码 | L4: (单据头)申请部门#名称 | M4: *(单据头)单据类型#编码 | N4: (单据头)单据类型#名称 | O4: *(单据头)费用承担组织#编码 | P4: (单据头)费用承担组织#名称 | Q4: *(单据头)费用承担部门#编码 | R4: (单据头)费用承担部门#名称 | S4: *(单据头)收款对象类型 | T4: *(单据头)收款对象#编码 | U4: (单据头)收款对象#名称 | V4: *(单据头)汇率类型#编码 | W4: (单据头)汇率类型#名称 | X4: *(单据头)本位币#编码 | Y4: (单据头)本位币#名称 | AA4: *报销明细(序号) | AB4: *(报销明细)费用项目#编码 | AC4: (报销明细)费用项目#名称 | AD4: *(报销明细)开始日期 | AE4: *(报销明细)结束日期 | AF4: *(报销明细)出发地 | AG4: *(报销明细)目的地 | AH4: (报销明细)差旅费类型#编码 | AI4: (报销明细)差旅费类型#名称 | AJ4: (报销明细)差旅费金额 | AK4: *(报销明细)发票类型 | AL4: (报销明细)税率% | AM4: (报销明细)申请报销金额 | AN4: *(报销明细)费用承担部门#编码 | AO4: (报销明细)费用承担部门#名称 | AP4: (报销明细)费用金额 | AQ4: *(报销明细)项目中心#编码 | AR4: (报销明细)项目中心#名称 | AS4: (报销明细)出行人及备注
A5: 范例 | B5: 100252 | C5: 45002 | D5: PRE001 | E5: 人民币 | F5: =IFERROR(VLOOKUP(G5,'索引'!M1:N4,2,FALSE),"") -> 100 | G5: 广州艮业信息科技有限公司 | H5: 出差 | I5: 159 | J5: 林思晴 | K5: =IFERROR(VLOOKUP(L5,'索引'!$I:$J,2,FALSE),"") | L5: 非标核算部 | M5: CLFBX002_SYS | N5: 差旅费报销单（2019新政） | O5: =$F$5 -> 100 | P5: =$G$5 -> 广州艮业信息科技有限公司 | Q5: =$K$5 | R5: =$L$5 -> 非标核算部 | S5: 员工 | T5: =$I$5 -> 159 | U5: =$J$5 -> 林思晴 | V5: HLTX01_SYS | W5: 固定汇率 | X5: PRE001 | Y5: 人民币 | Z5: 范例 | AA5: 1 | AB5: =IFERROR(VLOOKUP('员工报销单模板'!AC5,'索引'!$A$1:$B$62,2,FALSE),"") -> CI006.01 | AC5: 油费 | AD5: 44714 | AE5: 44721 | AF5: 广州 | AG5: 东莞 | AH5: =IFERROR(VLOOKUP(AI5,'索引'!$C$3:$D$8,2,FALSE),"") -> CLLX003 | AI5: 公路、水路等其他客票（中国） | AJ5: 552.16 | AK5: 普通发票 | AM5: =IF(AJ5<>0,AJ5,"") -> 552.16 | AN5: =IFERROR(VLOOKUP(AO5,'索引'!$I:$J,2,FALSE),"") | AO5: 生态战略中心 | AP5: =IF(AJ5<>0,AJ5,"") -> 552.16 | AQ5: =IFERROR(VLOOKUP('员工报销单模板'!AR5,'项目中心'!C:D,2,FALSE),"") -> 华南-粤-202502018 | AR5: 横沥极兔 | AS5: 调研乐山韵达
AA6: 2 | AB6: =IFERROR(VLOOKUP('员工报销单模板'!AC6,'索引'!$A$1:$B$62,2,FALSE),"") -> CI005.04 | AC6: 交通费 | AH6: =IFERROR(VLOOKUP(AI6,'索引'!$C$3:$D$8,2,FALSE),"") | AJ6: 1500 | AM6: =IF(AJ6<>0,AJ6,"") -> 1500 | AN6: =IFERROR(VLOOKUP(AO6,'索引'!$I:$J,2,FALSE),"") | AP6: =IF(AJ6<>0,AJ6,"") -> 1500 | AQ6: =IFERROR(VLOOKUP('员工报销单模板'!AR6,'项目中心'!C:D,2,FALSE),"")
AB7: =IFERROR(VLOOKUP('员工报销单模板'!AC7,'索引'!$A$1:$B$62,2,FALSE),"") | AH7: =IFERROR(VLOOKUP(AI7,'索引'!$C$3:$D$8,2,FALSE),"") | AM7: =IF(AJ7<>0,AJ7,"") | AN7: =IFERROR(VLOOKUP(AO7,'索引'!$I:$J,2,FALSE),"") | AP7: =IF(AJ7<>0,AJ7,"") | AQ7: =IFERROR(VLOOKUP('员工报销单模板'!AR7,'项目中心'!C:D,2,FALSE),"")
AB8: =IFERROR(VLOOKUP('员工报销单模板'!AC8,'索引'!$A$1:$B$62,2,FALSE),"") | AH8: =IFERROR(VLOOKUP(AI8,'索引'!$C$3:$D$8,2,FALSE),"") | AM8: =IF(AJ8<>0,AJ8,"") | AN8: =IFERROR(VLOOKUP(AO8,'索引'!$I:$J,2,FALSE),"") | AP8: =IF(AJ8<>0,AJ8,"") | AQ8: =IFERROR(VLOOKUP('员工报销单模板'!AR8,'项目中心'!C:D,2,FALSE),"")
AB9: =IFERROR(VLOOKUP('员工报销单模板'!AC9,'索引'!$A$1:$B$62,2,FALSE),"") | AH9: =IFERROR(VLOOKUP(AI9,'索引'!$C$3:$D$8,2,FALSE),"") | AM9: =IF(AJ9<>0,AJ9,"") | AN9: =IFERROR(VLOOKUP(AO9,'索引'!$I:$J,2,FALSE),"") | AP9: =IF(AJ9<>0,AJ9,"") | AQ9: =IFERROR(VLOOKUP('员工报销单模板'!AR9,'项目中心'!C:D,2,FALSE),"")
AB10: =IFERROR(VLOOKUP('员工报销单模板'!AC10,'索引'!$A$1:$B$62,2,FALSE),"") | AH10: =IFERROR(VLOOKUP(AI10,'索引'!$C$3:$D$8,2,FALSE),"") | AM10: =IF(AJ10<>0,AJ10,"") | AN10: =IFERROR(VLOOKUP(AO10,'索引'!$I:$J,2,FALSE),"") | AP10: =IF(AJ10<>0,AJ10,"") | AQ10: =IFERROR(VLOOKUP('员工报销单模板'!AR10,'项目中心'!C:D,2,FALSE),"")
AB11: =IFERROR(VLOOKUP('员工报销单模板'!AC11,'索引'!$A$1:$B$62,2,FALSE),"") | AH11: =IFERROR(VLOOKUP(AI11,'索引'!$C$3:$D$8,2,FALSE),"") | AM11: =IF(AJ11<>0,AJ11,"") | AN11: =IFERROR(VLOOKUP(AO11,'索引'!$I:$J,2,FALSE),"") | AP11: =IF(AJ11<>0,AJ11,"") | AQ11: =IFERROR(VLOOKUP('员工报销单模板'!AR11,'项目中心'!C:D,2,FALSE),"")
AB12: =IFERROR(VLOOKUP('员工报销单模板'!AC12,'索引'!$A$1:$B$62,2,FALSE),"") | AH12: =IFERROR(VLOOKUP(AI12,'索引'!$C$3:$D$8,2,FALSE),"") | AM12: =IF(AJ12<>0,AJ12,"") | AN12: =IFERROR(VLOOKUP(AO12,'索引'!$I:$J,2,FALSE),"") | AP12: =IF(AJ12<>0,AJ12,"") | AQ12: =IFERROR(VLOOKUP('员工报销单模板'!AR12,'项目中心'!C:D,2,FALSE),"")
AB13: =IFERROR(VLOOKUP('员工报销单模板'!AC13,'索引'!$A$1:$B$62,2,FALSE),"") | AH13: =IFERROR(VLOOKUP(AI13,'索引'!$C$3:$D$8,2,FALSE),"") | AM13: =IF(AJ13<>0,AJ13,"") | AN13: =IFERROR(VLOOKUP(AO13,'索引'!$I:$J,2,FALSE),"") | AP13: =IF(AJ13<>0,AJ13,"") | AQ13: =IFERROR(VLOOKUP('员工报销单模板'!AR13,'项目中心'!C:D,2,FALSE),"")
AB14: =IFERROR(VLOOKUP('员工报销单模板'!AC14,'索引'!$A$1:$B$62,2,FALSE),"") | AH14: =IFERROR(VLOOKUP(AI14,'索引'!$C$3:$D$8,2,FALSE),"") | AM14: =IF(AJ14<>0,AJ14,"") | AN14: =IFERROR(VLOOKUP(AO14,'索引'!$I:$J,2,FALSE),"") | AP14: =IF(AJ14<>0,AJ14,"") | AQ14: =IFERROR(VLOOKUP('员工报销单模板'!AR14,'项目中心'!C:D,2,FALSE),"")
AB15: =IFERROR(VLOOKUP('员工报销单模板'!AC15,'索引'!$A$1:$B$62,2,FALSE),"") | AH15: =IFERROR(VLOOKUP(AI15,'索引'!$C$3:$D$8,2,FALSE),"") | AM15: =IF(AJ15<>0,AJ15,"") | AN15: =IFERROR(VLOOKUP(AO15,'索引'!$I:$J,2,FALSE),"") | AP15: =IF(AJ15<>0,AJ15,"") | AQ15: =IFERROR(VLOOKUP('员工报销单模板'!AR15,'项目中心'!C:D,2,FALSE),"")
AB16: =IFERROR(VLOOKUP('员工报销单模板'!AC16,'索引'!$A$1:$B$62,2,FALSE),"") | AH16: =IFERROR(VLOOKUP(AI16,'索引'!$C$3:$D$8,2,FALSE),"") | AM16: =IF(AJ16<>0,AJ16,"") | AN16: =IFERROR(VLOOKUP(AO16,'索引'!$I:$J,2,FALSE),"") | AP16: =IF(AJ16<>0,AJ16,"") | AQ16: =IFERROR(VLOOKUP('员工报销单模板'!AR16,'项目中心'!C:D,2,FALSE),"")
AB17: =IFERROR(VLOOKUP('员工报销单模板'!AC17,'索引'!$A$1:$B$62,2,FALSE),"") | AH17: =IFERROR(VLOOKUP(AI17,'索引'!$C$3:$D$8,2,FALSE),"") | AM17: =IF(AJ17<>0,AJ17,"") | AN17: =IFERROR(VLOOKUP(AO17,'索引'!$I:$J,2,FALSE),"") | AP17: =IF(AJ17<>0,AJ17,"") | AQ17: =IFERROR(VLOOKUP('员工报销单模板'!AR17,'项目中心'!C:D,2,FALSE),"")
AB18: =IFERROR(VLOOKUP('员工报销单模板'!AC18,'索引'!$A$1:$B$62,2,FALSE),"") | AH18: =IFERROR(VLOOKUP(AI18,'索引'!$C$3:$D$8,2,FALSE),"") | AM18: =IF(AJ18<>0,AJ18,"") | AN18: =IFERROR(VLOOKUP(AO18,'索引'!$I:$J,2,FALSE),"") | AP18: =IF(AJ18<>0,AJ18,"") | AQ18: =IFERROR(VLOOKUP('员工报销单模板'!AR18,'项目中心'!C:D,2,FALSE),"")
... AB200: =IFERROR(VLOOKUP('员工报销单模板'!AC200,'索引'!$A$1:$B$62,2,FALSE),"") | AH200: =IFERROR(VLOOKUP(AI200,'索引'!$C$3:$D$8,2,FALSE),"") | AM200: =IF(AJ200<>0,AJ200,"") | AN200: =IFERROR(VLOOKUP(AO200,'索引'!$I:$J,2,FALSE),"") | AP200: =IF(AJ200<>0,AJ200,"") | AQ200: =IFERROR(VLOOKUP('员工报销单模板'!AR200,'项目中心'!C:D,2,FALSE),"")
AA201: 该行以下，没有设置公式 | AH201: =IFERROR(VLOOKUP(AI201,#REF!,2,FALSE),"")

Sheet 项目中心
B1: 编码 | C1: 项目名称 | D1: 编码
B2: 华南-粤-202202008 | C2: 大源韵达 | D2: 华南-粤-202202008 | E2: {=INDEX(C:C,SMALL(IF(ISNUMBER(FIND(CELL("contents"),$C$2:$C$4852)),ROW($C$2:$C$4852),4^8),ROW(C2)))&""} -> #N/A
B3: 华南-粤-202202007 | C3: 海珠南洲申通 | D3: 华南-粤-202202007 | E3: {=INDEX(C:C,SMALL(IF(ISNUMBER(FIND(CELL("contents"),$C$2:$C$4852)),ROW($C$2:$C$4852),4^8),ROW(C3)))&""} -> #N/A
B4: 华南-闽-202202006 | C4: 漳平共派新增接口（极兔+丰网） | D4: 华南-闽-202202006 | E4: {=INDEX(C:C,SMALL(IF(ISNUMBER(FIND(CELL("contents"),$C$2:$C$4852)),ROW($C$2:$C$4852),4^8),ROW(C4)))&""} -> #N/A
B5: 华南-粤-202202003 | C5: 番禺石碁申通 | D5: 华南-粤-202202003 | E5: {=INDEX(C:C,SMALL(IF(ISNUMBER(FIND(CELL("contents"),$C$2:$C$4852)),ROW($C$2:$C$4852),4^8),ROW(C5)))&""} -> #N/A
B6: 华南-滇-202202001 | C6: 昆明南窑共派（直线） | D6: 华南-滇-202202001 | E6: {=INDEX(C:C,SMALL(IF(ISNUMBER(FIND(CELL("contents"),$C$2:$C$4852)),ROW($C$2:$C$4852),4^8),ROW(C6)))&""} -> #N/A
B7: 华东-鲁-202202003 | C7: 青州圆通 | D7: 华东-鲁-202202003 | E7: {=INDEX(C:C,SMALL(IF(ISNUMBER(FIND(CELL("contents"),$C$2:$C$4852)),ROW($C$2:$C$4852),4^8),ROW(C7)))&""} -> #N/A
B8: 华南-粤-202201001 | C8: 沙井中通-增补 | D8: 华南-粤-202201001 | E8: {=INDEX(C:C,SMALL(IF(ISNUMBER(FIND(CELL("contents"),$C$2:$C$4852)),ROW($C$2:$C$4852),4^8),ROW(C8)))&""} -> #N/A
B9: 华东-鲁-202202002 | C9: 聊城百世 | D9: 华东-鲁-202202002 | E9: {=INDEX(C:C,SMALL(IF(ISNUMBER(FIND(CELL("contents"),$C$2:$C$4852)),ROW($C$2:$C$4852),4^8),ROW(C9)))&""} -> #N/A
B10: 华东-苏-202202001 | C10: 如东共派 | D10: 华东-苏-202202001 | E10: {=INDEX(C:C,SMALL(IF(ISNUMBER(FIND(CELL("contents"),$C$2:$C$4852)),ROW($C$2:$C$4852),4^8),ROW(C10)))&""} -> #N/A
B11: 华南-赣-202202001 | C11: 赣州于都中通（直线） | D11: 华南-赣-202202001 | E11: {=INDEX(C:C,SMALL(IF(ISNUMBER(FIND(CELL("contents"),$C$2:$C$4852)),ROW($C$2:$C$4852),4^8),ROW(C11)))&""} -> #N/A
B12: 华南-粤-202202002 | C12: 塘厦丰网 | D12: 华南-粤-202202002 | E12: {=INDEX(C:C,SMALL(IF(ISNUMBER(FIND(CELL("contents"),$C$2:$C$4852)),ROW($C$2:$C$4852),4^8),ROW(C12)))&""} -> #N/A
B13: 华东-皖-202201015 | C13: 合肥香港街网格仓（直线） | D13: 华东-皖-202201015 | E13: {=INDEX(C:C,SMALL(IF(ISNUMBER(FIND(CELL("contents"),$C$2:$C$4852)),ROW($C$2:$C$4852),4^8),ROW(C13)))&""} -> #N/A
... B4852: 新兴-浙-202608017 | C4852: 义乌金华中通云仓转运中心 | D4852: 新兴-浙-202608017 | E4852: {=INDEX(C:C,SMALL(IF(ISNUMBER(FIND(CELL("contents"),$C$2:$C$4852)),ROW($C$2:$C$4852),4^8),ROW(C4852)))&""} -> #NUM!

Sheet 索引
A1: 直接人工 | B1: 0805 | C1: FTravelType#Name | D1: FTravelType | E1: FInvoiceType | H1: 0002 | I1: 艮业_董事长 | J1: 0002 | L1: 100 | M1: 广州艮业信息科技有限公司 | N1: 100
A2: 社保 | B2: 0806 | C2: (报销明细)差旅费类型#名称 | D2: (报销明细)差旅费类型#编码 | E2: *(报销明细)发票类型 | F2: 对应发票 | H2: 0003 | I2: 艮业_生态战略中心 | J2: 0003 | L2: 101 | M2: 广州骏业智能科技有限公司
A3: 公积金 | B3: 0807 | C3: 航空运输（中国） | D3: CLLX001 | E3: 机票 | F3: 飞机票纸质或者电子行程单 | H3: 0003-0001 | I3: 艮业_产业园项目部 | J3: 0003-0001 | L3: 102 | M3: 广州艮业信息科技有限公司海宁分公司
A4: 其他 | B4: 1030 | C4: 铁路车票（中国） | D4: CLLX002 | E4: 火车票 | F4: 取票机的报销凭证（蓝色硬质纸票），人口售票口的票据，电子铁路客票 | H4: 0004 | I4: 艮业_营销中心 | J4: 0004 | L4: 103 | M4: 凌跃科技（嘉兴）有限公司 | N4: 103
A5: 应付职工工资 | B5: CI001 | C5: 公路、水路等其他客票（中国） | D5: CLLX003 | E5: 其他运输票 | F5: 卷式出租车发票、流水针式打印路桥费，定额水陆发票，手撕地铁、公交、出租车等运输发票 | H5: 0004-0001 | I5: 艮业_国内销售部 | J5: 0004-0001 | L5: 104 | M5: 广州汇佳机械设备有限公司 | N5: 104
A6: 社会保险费 | B6: CI002 | C6: 其他取得电子普票的旅客运输（中国） | D6: CLLX004 | E6: 普通发票 | F6: 电子普通发票、纸质普通发票（只有红色一联，电子票有普通发票字样） | H6: 0004-0001-0001 | I6: 艮业_商务部 | J6: 0004-0001-0001 | L6: 105 | M6: 佛山坎业科技有限公司
A7: 住房公积金 | B7: CI003 | C7: 住宿费 | D7: CLLX005 | E7: 增值税发票 | F7: 增值税专用发票（纸质票有绿色联和红色联，电子票有专用发票字样） | H7: 0004-0001-0002 | I7: 艮业_华南大区 | J7: 0004-0001-0002 | L7: 108 | M7: 芜湖领航智能设备有限公司
A8: 职工福利费 | B8: CI004 | C8: 其他费用 | D8: CLLX006 | E8: 其他 | F8: 手写收据、手写收条、付款截图、医院收据、政府基金收据 | H8: 0004-0001-0002-0001 | I8: 艮业_粤西省区 | J8: 0004-0001-0002-0001
A9: 差旅费 | B9: CI005 | H9: 0004-0001-0002-0002 | I9: 艮业_粤东省区 | J9: 0004-0001-0002-0002
A10: 住宿费 | B10: CI005.01 | H10: 0004-0001-0002-0003 | I10: 艮业_琼桂省区 | J10: 0004-0001-0002-0003
A11: 铁路费 | B11: CI005.02 | H11: 0004-0001-0002-0004 | I11: 艮业_江西省区 | J11: 0004-0001-0002-0004
A12: 机票费 | B12: CI005.03 | H12: 0004-0001-0003 | I12: 艮业_华东大区 | J12: 0004-0001-0003
A13: 交通费 | B13: CI005.04 | H13: 0004-0001-0003-0001 | I13: 艮业_安徽省区 | J13: 0004-0001-0003-0001
A14: 差旅费-其他费用 | B14: CI005.05 | H14: 0004-0001-0003-0002 | I14: 艮业_江苏省区 | J14: 0004-0001-0003-0002
A15: 出差补贴 | B15: CI005.06 | H15: 0004-0001-0003-0003 | I15: 艮业_山东省区 | J15: 0004-0001-0003-0003
A16: 车辆费用 | B16: CI006 | H16: 0004-0001-0003-0004 | I16: 艮业_福建省区 | J16: 0004-0001-0003-0004
A17: 油费 | B17: CI006.01 | H17: 0004-0001-0003-0005 | I17: 艮业_浙沪省区 | J17: 0004-0001-0003-0005
A18: 路桥费 | B18: CI006.02 | H18: 0004-0001-0004 | I18: 艮业_西南大区 | J18: 0004-0001-0004
A19: 停车费 | B19: CI006.03 | H19: 0004-0001-0004-0001 | I19: 艮业_云贵省区 | J19: 0004-0001-0004-0001
A20: 车辆维修及保养 | B20: CI006.04 | H20: 0004-0001-0004-0002 | I20: 艮业_西北省区 | J20: 0004-0001-0004-0002
... A62: 年检/审计费 | B62: CI060 | H62: 0007-0004-0002 | I62: 艮业_售后组 | J62: 0007-0004-0002
H63: 0007-0005 | I63: 艮业_北美分部 | J63: 0007-0005
H64: 0007-0005-0001 | I64: 艮业_售后组 | J64: 0007-0005-0001
H65: 0007-0005-0002 | I65: 艮业_业务组 | J65: 0007-0005-0002
H66: 0008 | I66: 艮业_技术研发中心 | J66: 0008
H67: 0008-0001 | I67: 艮业_智能分拣研发一部 | J67: 0008-0001
H68: 0008-0001-0001 | I68: 艮业_综合应用组 | J68: 0008-0001-0001
H69: 0008-0001-0002 | I69: 艮业_自动供包组 | J69: 0008-0001-0002
H70: 0008-0001-0003 | I70: 艮业_分拣算法组 | J70: 0008-0001-0003
H71: 0008-0002 | I71: 艮业_智能分拣研发二部 | J71: 0008-0002
H72: 0008-0002-0001 | I72: 艮业_工控 | J72: 0008-0002-0001
H73: 0008-0002-0002 | I73: 艮业_软件 | J73: 0008-0002-0002
H74: 0008-0002-0003 | I74: 艮业_设计 | J74: 0008-0002-0003
... H194: 0004-0005-0002 | I194: 艮业_规划设计部_华南区&西南区 | J194: 0004-0005-0002
